snake_game/__init__.py
snake_game/server.py
snake_game/static/game.js
snake_game/static/index.html
snake_game/static/style.css
snake_game_zh-1.0.0.dist-info/licenses/LICENSE
snake_game_zh-1.0.0.dist-info/METADATA
snake_game_zh-1.0.0.dist-info/WHEEL
snake_game_zh-1.0.0.dist-info/entry_points.txt
snake_game_zh-1.0.0.dist-info/top_level.txt
snake_game_zh-1.0.0.dist-info/RECORD
