Metadata-Version: 2.4
Name: snake-game-zh
Version: 1.0.0
Summary: 一个经典的贪吃蛇小游戏，使用HTML5 Canvas实现
Home-page: https://github.com/yourusername/snake-game
Author: Your Name
Author-email: your.email@example.com
Project-URL: Bug Reports, https://github.com/yourusername/snake-game/issues
Project-URL: Source, https://github.com/yourusername/snake-game
Keywords: snake game,game,arcade,html5,canvas
Classifier: Development Status :: 4 - Beta
Classifier: Intended Audience :: End Users/Desktop
Classifier: Topic :: Games/Entertainment :: Arcade
Classifier: License :: OSI Approved :: MIT License
Classifier: Programming Language :: Python :: 3
Classifier: Programming Language :: Python :: 3.7
Classifier: Programming Language :: Python :: 3.8
Classifier: Programming Language :: Python :: 3.9
Classifier: Programming Language :: Python :: 3.10
Classifier: Programming Language :: Python :: 3.11
Requires-Python: >=3.7
License-File: LICENSE
Dynamic: author
Dynamic: author-email
Dynamic: classifier
Dynamic: description
Dynamic: description-content-type
Dynamic: home-page
Dynamic: keywords
Dynamic: license-file
Dynamic: project-url
Dynamic: requires-python
Dynamic: summary
